encrypted_env_loader/__init__.py
encrypted_env_loader/cli.py
encrypted_env_loader/core.py
encrypted_env_loader/py.typed
encrypted_env_loader-0.3.0.dist-info/licenses/LICENSE
encrypted_env_loader-0.3.0.dist-info/METADATA
encrypted_env_loader-0.3.0.dist-info/WHEEL
encrypted_env_loader-0.3.0.dist-info/entry_points.txt
encrypted_env_loader-0.3.0.dist-info/top_level.txt
encrypted_env_loader-0.3.0.dist-info/RECORD
