Metadata-Version: 2.4
Name: encrypted-env-loader
Version: 0.3.0
Summary: Securely load and manage encrypted environment variables
Author-email: Isaac Harrison Gutekunst <isaac@supercortex.io>
License: MIT
Project-URL: Homepage, https://github.com/igutekunst/encrypted-env-loader
Project-URL: Repository, https://github.com/igutekunst/encrypted-env-loader
Project-URL: Issues, https://github.com/igutekunst/encrypted-env-loader/issues
Keywords: environment,encryption,security,dotenv,configuration
Classifier: Development Status :: 4 - Beta
Classifier: Intended Audience :: Developers
Classifier: License :: OSI Approved :: MIT License
Classifier: Programming Language :: Python :: 3
Classifier: Programming Language :: Python :: 3.9
Classifier: Programming Language :: Python :: 3.10
Classifier: Programming Language :: Python :: 3.11
Classifier: Programming Language :: Python :: 3.12
Classifier: Topic :: Security :: Cryptography
Classifier: Topic :: Software Development :: Libraries :: Python Modules
Classifier: Topic :: System :: Systems Administration
Requires-Python: >=3.9
License-File: LICENSE
Requires-Dist: cryptography>=41.0.0
Requires-Dist: click>=8.0.0
Requires-Dist: python-dotenv>=1.0.0
Requires-Dist: keyring>=24.0.0
Provides-Extra: dev
Requires-Dist: pytest>=7.0.0; extra == "dev"
Requires-Dist: pytest-cov>=4.0.0; extra == "dev"
Requires-Dist: black>=23.0.0; extra == "dev"
Requires-Dist: isort>=5.12.0; extra == "dev"
Requires-Dist: flake8>=6.0.0; extra == "dev"
Requires-Dist: mypy>=1.0.0; extra == "dev"
Provides-Extra: keyring
Requires-Dist: keyring>=24.0.0; extra == "keyring"
Dynamic: license-file
